pygenerategui/__init__.py
pygenerategui/gui_component.py
pygenerategui/pggui_app.py
pygenerategui-0.0.8.dist-info/LICENSE
pygenerategui-0.0.8.dist-info/METADATA
pygenerategui-0.0.8.dist-info/WHEEL
pygenerategui-0.0.8.dist-info/top_level.txt
pygenerategui-0.0.8.dist-info/RECORD
