Metadata-Version: 2.1
Name: pygenerategui
Version: 0.0.8
Summary: Utility for generating simple GUI to execute Python code
Home-page: https://github.com/jaredmassey/pygenerategui
Author: Jared Massey
Author-email: jared@jaredmassey.com
License: UNKNOWN
Platform: UNKNOWN
Classifier: Programming Language :: Python :: 3
Classifier: License :: OSI Approved :: MIT License
Classifier: Operating System :: OS Independent
Requires-Python: >=3.9
License-File: LICENSE
